dnslink/__init__.py
dnslink/__main__.py
dnslink-1.0.3.dist-info/LICENSE
dnslink-1.0.3.dist-info/METADATA
dnslink-1.0.3.dist-info/WHEEL
dnslink-1.0.3.dist-info/entry_points.txt
dnslink-1.0.3.dist-info/top_level.txt
dnslink-1.0.3.dist-info/RECORD
