Metadata-Version: 2.1
Name: dnslink
Version: 1.0.3
Summary: Python implementation of DNSLink protocol
Home-page: https://github.com/filips123/DNSLinkPy/
Author: Filip Š
Author-email: projects@filips.si
License: MIT
Keywords: dns,dnslink,content-addressing,web3,decentralized
Platform: UNKNOWN
Classifier: Development Status :: 5 - Production/Stable
Classifier: Intended Audience :: Developers
Classifier: License :: OSI Approved :: MIT License
Classifier: Programming Language :: Python :: 3
Classifier: Topic :: Internet :: Name Service (DNS)
Classifier: Topic :: Scientific/Engineering :: Interface Engine/Protocol Translator
Classifier: Topic :: Security :: Cryptography
Classifier: Topic :: Software Development :: Libraries
Classifier: Topic :: Utilities
Requires-Python: >= 3.4
Requires-Dist: dnspython (<3.0.0,>=1.0.0)
Provides-Extra: lint
Requires-Dist: pylint ; extra == 'lint'
Provides-Extra: test
Requires-Dist: pytest ; extra == 'test'
Requires-Dist: pytest-cov ; extra == 'test'
